Workbook

Sheet Assumptions
A1: ZENITH M&A MODEL - ASSUMPTIONS
A3: Thing | B3: Value | C3: Meaning
A4: Revenue (sales) | B4: 280 | C4: Zenith makes $280M this year | D4: All figures in $ millions. Percentages are linked to future forecast tabs.
A5: Gross Margin | B5: 0.72 | C5: Keeps 72¢ per $1 earned
A6: Operating Expenses | B6: 0.54 | C6: Spends 54¢ per $1 to run the business
A7: D&A | B7: 0.03 | C7: Equipment/software wearing out
A8: CapEx | B8: 0.02 | C8: Buys new tools & tech
A9: Working Capital | B9: 0.02 | C9: Short-term cash used
A10: Tax Rate | B10: 0.25 | C10: Pays this to government
A11: Revenue Growth | B11: 12%, 11%, 10%, 9%, 8% | C11: Grows slower each year
A12: OpEx % | B12: 54%, 52%, 50%, 49%, 48% | C12: Becomes more efficient
A14: 5-Year Growth Assumptions
A15: Year | B15: 1 | C15: 2 | D15: 3 | E15: 4 | F15: 5
A16: Revenue Growth | C16: 0.12 | D16: 0.11 | E16: 0.1 | F16: 0.09
A17: OpEx % | B17: 0.54 | C17: 0.52 | D17: 0.5 | E17: 0.49 | F17: 0.48

Sheet Financials
A1: Zenith – Cost of Capital (WACC)
A2: Line Item | B2: Year 1 | C2: Year 2 | D2: Year 3 | E2: Year 4 | F2: Year 5
A3: Revenue($M) | B3: =Assumptions!B4 -> 280 | C3: =B3*(1+Assumptions!C16) -> 313.6 | D3: =C3*(1+Assumptions!D16) -> 348.096 | E3: =D3*(1+Assumptions!E16) -> 382.9056 | F3: =E3*(1+Assumptions!F16) -> 417.3671
A4: COGS(28%) | B4: =B3*(1-Assumptions!B5) -> 78.4 | C4: =C3*(1-Assumptions!B5) -> 87.808 | D4: =D3*(1-Assumptions!B5) -> 97.46688 | E4: =E3*(1-Assumptions!B5) -> 107.21357 | F4: =F3*(1-Assumptions!B5) -> 116.86279
A5: Gross Profit | B5: =B3-B4 -> 201.6 | C5: =C3-C4 -> 225.792 | D5: =D3-D4 -> 250.62912 | E5: =E3-E4 -> 275.69203 | F5: =F3-F4 -> 300.50431
A6: Operating Expenses | B6: =B3*Assumptions!B17 -> 151.2 | C6: =C3*Assumptions!C17 -> 163.072 | D6: =D3*Assumptions!D17 -> 174.048 | E6: =E3*Assumptions!E17 -> 187.62374 | F6: =F3*Assumptions!F17 -> 200.33621
A7: EBITDA | B7: =B5-B6 -> 50.4 | C7: =C5-C6 -> 62.72 | D7: =D5-D6 -> 76.58112 | E7: =E5-E6 -> 88.068288 | F7: =F5-F6 -> 100.1681
A8: D&A(3%) | B8: =B3*Assumptions!B7 -> 8.4 | C8: =C3*Assumptions!B7 -> 9.408 | D8: =D3*Assumptions!B7 -> 10.44288 | E8: =E3*Assumptions!B7 -> 11.487168 | F8: =F3*Assumptions!B7 -> 12.521013
A9: EBIT | B9: =B7-B8 -> 42 | C9: =C7-C8 -> 53.312 | D9: =D7-D8 -> 66.13824 | E9: =E7-E8 -> 76.58112 | F9: =F7-F8 -> 87.647092
A10: Taxes(25%) | B10: =B9*Assumptions!B10 -> 10.5 | C10: =C9*Assumptions!B10 -> 13.328 | D10: =D9*Assumptions!B10 -> 16.53456 | E10: =E9*Assumptions!B10 -> 19.14528 | F10: =F9*Assumptions!B10 -> 21.911773
A11: Net Income | B11: =B9-B10 -> 31.5 | C11: =C9-C10 -> 39.984 | D11: =D9-D10 -> 49.60368 | E11: =E9-E10 -> 57.43584 | F11: =F9-F10 -> 65.735319

Sheet WACC_Calc
A1: Zenith SaaS - Weighted Average Cost of Capital (WACC)
A2: Input | B2: Symbol | C2: Value
A3: Risk-Free Rate | B3: Rf | C3: 0.045
A4: Market-Risk Premium | B4: MRP | C4: 0.06
A5: Beta | C5: 1.1
A6: CAPM | B6: Re | C6: =C3 + (C4*C5) -> 0.111
A7: Cost of Debt | B7: Rd | C7: 0
A8: Tax Rate | B8: T | C8: 0.25
A9: Equity Weight | B9: E/(D+E) | C9: 1
A10: Debt Weight | B10: D/(D+E) | C10: 0
A11: WACC | C11: =(C9*C6)+(C10*C7*(1-C8)) -> 0.111

Sheet Trading Comps
A1: Trading Comparables - SaaS (Training set )
A2: Company | B2: Stock Price ($) | C2: Shares (M) | D2: Equity Value ($M) | E2: Debt | F2: Cash | G2: Enterprise Value (EV) | H2: Revenue | I2: EBITDA | J2: EV/Revenue | K2: EV/EBITDA
A3: Salesforce | B3: 240 | C3: 980 | D3: =B3*C3 -> 235200 | E3: 10000 | F3: 5000 | G3: =D3+E3-F3 -> 240200 | H3: 35000 | I3: 9000 | J3: =G3/H3 -> 6.8628571 | K3: =G3/I3 -> 26.688889
A4: Workday | B4: 270 | C4: 260 | D4: =B4*C4 -> 70200 | E4: 3000 | F4: 2000 | G4: =D4+E4-F4 -> 71200 | H4: 8000 | I4: 1200 | J4: =G4/H4 -> 8.9 | K4: =G4/I4 -> 59.333333
A5: ServiceNow | B5: 700 | C5: 210 | D5: =B5*C5 -> 147000 | E5: 2000 | F5: 1000 | G5: =D5+E5-F5 -> 148000 | H5: 10000 | I5: 3000 | J5: =G5/H5 -> 14.8 | K5: =G5/I5 -> 49.333333
A6: Adobe | B6: 500 | C6: 450 | D6: =B6*C6 -> 225000 | E6: 4000 | F6: 2000 | G6: =D6+E6-F6 -> 227000 | H6: 20000 | I6: 7000 | J6: =G6/H6 -> 11.35 | K6: =G6/I6 -> 32.428571
A7: Datadog | B7: 120 | C7: 320 | D7: =B7*C7 -> 38400 | E7: 1000 | F7: 500 | G7: =D7+E7-F7 -> 38900 | H7: 3000 | I7: 700 | J7: =G7/H7 -> 12.966667 | K7: =G7/I7 -> 55.571429
A9: Company | B9: EV/Revenue | C9: EV/EBITDA
A10: Median | B10: =MEDIAN(J3:J7) -> 11.35 | C10: =MEDIAN(K3:K7) -> 49.333333
A12: Metric | B12: Zenith Value($M) | C12: Median Multiple | D12: Implied Enterprise Value ($M)
A13: Revenue | B13: =Financials!B3 -> 280 | C13: 11.35 | D13: =B13*C13 -> 3178
A14: EBITDA | B14: =Financials!B7 -> 50.4 | C14: 49.3 | D14: =B14*C14 -> 2484.72
A16: Average value | B16: =(D13+D14)/2 -> 2831.36
A17: This suggest Zenith's valuation range is about 2.8B which is rougly 10-11x revenue and 49x EBITDA with typical SaaS peers.

Sheet Precedent Transactions
A1: Zenith SaaS – Precedent Transactions (M&A Comparables)
A2: Company (Target) | B2: Acquirer | C2: Year | D2: Deal Value ($M) | E2: Revenue ($M) | F2: EBITDA($M) | G2: EV/Revenue | H2: EV/EBITDA
A3: Slack | B3: Salesforce | C3: 2021 | D3: 27700 | E3: 900 | F3: 0 | G3: 30.8 | H3: -
A4: Tableau | B4: Salesforce | C4: 2019 | D4: 15700 | E4: 1400 | F4: 280 | G4: 11.2 | H4: 56.1
A5: Mulesoft | B5: Salesforce | C5: 2018 | D5: 6500 | E5: 296 | F5: 36 | G5: 22 | H5: 180.6
A6: Marketo | B6: Adobe | C6: 2018 | D6: 4750 | E6: 321 | F6: 53 | G6: 14.8 | H6: 89.6
A7: Qualtrics | B7: Adobe | C7: 2019 | D7: 8000 | E7: 400 | F7: 75 | G7: 20 | H7: 106.7
A9: Metric | B9: Median Multiple
A10: EV/Revenue | B10: =MEDIAN(G3:G7) -> 20
A11: EvV/EBITDA | B11: =MEDIAN(H4:H7) -> 98.15
A13: Metric | B13: Zenith Value($M) | C13: Median Multiple | D13: Implied Enterprise Value ($M)
A14: Revenue | B14: 280 | C14: 20 | D14: =B14*C14 -> 5600
A15: EBITDA | B15: 50.4 | C15: 98.15 | D15: =B15*C15 -> 4946.76
A16: Average Value | D16: =(D14+D15)/2 -> 5273.38
A17: Based on recent SaaS M&A deals , Zenith’s implied enterprise value ranges between $4.9B and $5.6B, with an average of ~$5.3B.This is higher than the Trading Comps valuation (~$2.8B), reflecting the premium buyers pay for full ownership in acquisitions.

Sheet DCF Analysis
A1: Zenith SaaS – Discounted Cash Flow (DCF) Valuation
A2: Item | B2: Year 1 | C2: Year 2 | D2: Year 3 | E2: Year 4 | F2: Year 5
A3: EBIT($M) | B3: =Financials!B9 -> 42 | C3: =Financials!C9 -> 53.312 | D3: =Financials!D9 -> 66.13824 | E3: =Financials!E9 -> 76.58112 | F3: =Financials!F9 -> 87.647092 | G3: All Values in $M
A4: Tax(25%) | B4: =B3*25% -> 10.5 | C4: =C3*25% -> 13.328 | D4: =D3*25% -> 16.53456 | E4: =E3*25% -> 19.14528 | F4: =F3*25% -> 21.911773
A5: NOPAT (EBIT -Tax) | B5: =B3-B4 -> 31.5 | C5: =C3-C4 -> 39.984 | D5: =D3-D4 -> 49.60368 | E5: =E3-E4 -> 57.43584 | F5: =F3-F4 -> 65.735319
A6: D&A | B6: =Financials!B8 -> 8.4 | C6: =Financials!C8 -> 9.408 | D6: =Financials!D8 -> 10.44288 | E6: =Financials!E8 -> 11.487168 | F6: =Financials!F8 -> 12.521013
A7: CapEx | B7: =Financials!B3*2% -> 5.6 | C7: =Financials!C3*2% -> 6.272 | D7: =Financials!D3*2% -> 6.96192 | E7: =Financials!E3*2% -> 7.658112 | F7: =Financials!F3*2% -> 8.3473421
A8: Change in Working Captial | B8: 0 | C8: =(Financials!C3-Financials!B3)*2% -> 0.672 | D8: =(Financials!D3-Financials!C3)*2% -> 0.68992 | E8: =(Financials!E3-Financials!D3)*2% -> 0.696192 | F8: =(Financials!F3-Financials!E3)*2% -> 0.68923008
A9: Free Cash Flow | B9: =B5 + B6 -B7-B8 -> 34.3 | C9: =C5 + C6 -C7-C8 -> 42.448 | D9: =D5 + D6 -D7-D8 -> 52.39472 | E9: =E5 + E6 -E7-E8 -> 60.568704 | F9: =F5 + F6 -F7-F8 -> 69.21976
A10: Discount Factor | B10: =1/(1+WACC_Calc!C11)^1 -> 0.90009001 | C10: =1/(1+WACC_Calc!C11)^2 -> 0.81016202 | D10: =1/(1+WACC_Calc!C11)^3 -> 0.72921874 | E10: =1/(1+WACC_Calc!C11)^4 -> 0.65636251 | F10: =1/(1+WACC_Calc!C11)^5 -> 0.59078533
A11: Present Value of FCF | B11: =B9*B10 -> 30.873087 | C11: =C9*C10 -> 34.389758 | D11: =D9*D10 -> 38.207212 | E11: =E9*E10 -> 39.755026 | F11: =F9*F10 -> 40.894019
A13: Total PV of 5 years | B13: =B11+C11+D11+E11+F11 -> 184.1191
A14: Terminal Value | B14: =F5*(1+3%)/(11%-3%) -> 846.34223 | C14: Taking g=3%
A15: Present Value of TV | B15: =B14/(1+WACC_Calc!C11)^5 -> 500.00658
A16: Enterprise Value | B16: =B15+B13 -> 684.12568
A18: Scenario | B18: WACC | C18: g(%) | D18: Result
A19: Low DCF | B19: 0.12 | C19: 0.02 | D19: =(F9*(1+2%))/(12%-2%) -> 706.04155
A20: Base DCF | B20: 0.111 | C20: 0.03 | D20: =(F9*(1+3%))/(11.1%-3%) -> 880.20188
A21: High DCF | B21: 0.1 | C21: 0.04 | D21: =(F9*(1+4%))/(10%-4%) -> 1199.8092

Sheet Valuation Summary
A1: Zenith SaaS – Valuation Summary & Recommendation
A2: Method | B2: Valuation source | C2: Low($M) | D2: High($M) | E2: Midpoint Enterprise Value($M)
A3: Trading Comparables | B3: Market multiples of SaaS peers | C3: ='Trading Comps'!D14 -> 2484.72 | D3: ='Trading Comps'!D13 -> 3178 | E3: ='Trading Comps'!B16 -> 2831.36
A4: Precedent Transactions | B4: M&A deal values for SaaS companies | C4: ='Precedent Transactions'!D15 -> 4946.76 | D4: ='Precedent Transactions'!D14 -> 5600 | E4: ='Precedent Transactions'!D16 -> 5273.38
A5: DCF | B5: Fiture Cash flow based valuation | C5: ='DCF Analysis'!D19 -> 706.04155 | D5: ='DCF Analysis'!D21 -> 1199.8092 | E5: ='DCF Analysis'!D20 -> 880.20188
A6: Average | B6: Equal-Weighted | C6: =AVERAGE(C3:C5) -> 2712.5072 | D6: =AVERAGE(D3:D5) -> 3325.9364 | E6: =AVERAGE(E3:E5) -> 2994.9806
A7: Weighted Value | B7: 50% Precedent, 35% Comps, 15% DCF | C7: =(35%*C3)+(50%*C4)+(15%*C5) -> 3448.9382 | D7: =(35%*D3)+(50%*D4)+(15%*D5) -> 4092.2714 | E7: =(35%*E3)+(50%*E4)+(15%*E5) -> 3759.6963

Sheet Strategic m&A model
A1: Strategic M&A Model – Salesforce Acquisition of Zenith SaaS
A2: Item | B2: Buyer(Salesforce) | C2: Target(Zenith)
A3: EPS | B3: 6 | C3: $0.63 (31.5M NI/ 50M Shares)
A4: Net Income | B4: 14400 | C4: =Financials!B11 -> 31.5 | D4: ($M)
A5: Shares Outstanding | B5: 2400 | C5: 50
A6: Deal Value | B6: $2.4B (cash) | C6: -
A7: Book Equity | B7: - | C7: 500
A8: Goodwill | B8: - | C8: 1900
A9: Goodwill Amortization Period | B9: - | C9: 7 years
A10: Annual Amortization | B10: - | C10: 271
A11: Integration Costs | B11: - | C11: 75
A13: Year 1 Pro Forma Section
A14: Item | B14: Result
A15: Buyer Standalone Net Income | B15: =B4 -> 14400
A16: Target Net Income | B16: =C4 -> 31.5
A17: Combined Pre-Amortization | B17: =B15+B16 -> 14431.5
A18: Less: Goodwill Amortization | B18: =C10 -> 271
A19: Less: Integration Costs | B19: =C11 -> 75
A20: Pro Forma Net Income | B20: =B17-B18-B19 -> 14085.5
A21: Combined shares Outstanding | B21: =B5 + C5 -> 2450
A22: Pro Forma EPS | B22: =B20/B21 -> 5.7491837
A23: Buyer Standalone EPS | B23: =B3 -> 6
A24: EPS Change | B24: =B22-B23 -> -0.25081633
A26: 3- Year EPS Bridge
A27: Year | B27: Stanalone EPS | C27: Zenith Growth + Synergies | D27: Amortization & Integration impact | E27: Pro Forma EPS | F27: Dilution
A28: 1 | B28: =B3 -> 6 | C28: 0.03 | D28: -0.14 | E28: =B28+C28+D28 -> 5.89 | F28: =E28-B28 -> -0.11
A29: 2 | B29: =B3*1.05 -> 6.3 | C29: 0.06 | D29: -0.11 | E29: =B29+C29+D29 -> 6.25 | F29: =E29-B29 -> -0.05
A30: 3 | B30: =B3*1.1 -> 6.6 | C30: 0.09 | D30: 0 | E30: =B30+C30+D30 -> 6.69 | F30: =E30-B30 -> 0.09

Sheet Recap LBO Model
A1: Zenith SaaS – Leveraged Recap (LBO) Model
A2: Item | B2: Amount ($ M)
A3: Founder dividend (cash out) | B3: 700
A4: Transaction fees (legal, banking) | B4: 100
A5: Cash retained (on balance sheet) | B5: 100
A6: Total | B6: =SUM(B3:B5) -> 900
A8: Sources | B8: Amount ($ M)
A9: PE equity investment | B9: 700
A10: Debt financing (6%) | B10: 200
A11: Total | B11: =SUM(B9:B10) -> 900
A13: Debt Schedule (5-Year Hold)
A14: Year | B14: Opening Debt | C14: Interest (6%) | D14: Debt Paydown | E14: Closing Debt | F14: EBITDA | G14: Leverage
A15: 1 | B15: 200 | C15: 12 | D15: 20 | E15: 180 | F15: 50 | G15: =B15/F15 -> 4
A16: 2 | B16: 180 | C16: 10.8 | D16: 20 | E16: 160 | F16: 53 | G16: =B16/F16 -> 3.3962264
A17: 3 | B17: 160 | C17: 9.6 | D17: 20 | E17: 140 | F17: 56 | G17: =B17/F17 -> 2.8571429
A18: 4 | B18: 140 | C18: 8.4 | D18: 20 | E18: 120 | F18: 59 | G18: =B18/F18 -> 2.3728814
A19: 5 | B19: 120 | C19: 7.2 | D19: 20 | E19: 100 | F19: 62 | G19: =B19/F19 -> 1.9354839 | H19: Leverage drops from ~4 × to ~1.6 × — healthy de-leveraging.
A21: Pro Forma P&L (Impact of Debt)
A22: Item | B22: Result
A23: EBITDA (Year 1) | B23: =Financials!B7 -> 50.4
A24: Less: Interest Expense | B24: =B15*0.06 -> 12
A25: EBT | B25: =F15-C15 -> 38
A26: Taxes (25%) | B26: =B25*25% -> 9.5
A27: Net Income | B27: =B25-B26 -> 28.5
A28: Free Cash Flow (approx.) | B28: =B27-D15 -> 8.5
A30: Exit Analysis (Year 5)
A31: Metric | B31: Result
A32: Year 5 EBITDA | B32: =F19 -> 62
A33: Exit multiple | B33: 9 | C33: (assumed 9x)
A34: Enterprise Value (Exit | B34: =B32*B33 -> 558
A35: Less: Debt (Year 5) | B35: 100
A36: Equity Value (Exit) | B36: =B34-B35 -> 458
A37: PE ownership | B37: 0.4
A38: PE proceeds | B38: =B36*B37 -> 183.2
A39: Initial PE investment | B39: 700
A40: Money Multiple | B40: =B38/B39 -> 0.26171429

Sheet Strategic sale vs Recap LBO
A1: Zenith SaaS – Strategic Sale vs. Leveraged Recap Comparison
A2: Factor | B2: Strategic Sale | C2: Leveraged Recap
A3: Founder Liquidity | B3: Full and immediate (~$1.44 B) | C3: Partial ($700 M cash + 50% equity retained)
A4: Timing | B4: 4–6 months to close | C4: 3–4 months to close + 5-year hold
A5: Risk Profile | B5: Low (cash deal, no leverage) | C5: High (leverage, market risk)
A6: Upside | B6: None (founders exit) | C6: Significant if company grows + multiples hold
A7: PE IRR (Base) | B7: N/A | C7: ~8–10 % → unacceptable
A8: PE IRR (Bull) | B8: N/A | C8: ~15–20 % → acceptable only if market stays strong
A9: Downside Risk | B9: Minimal (buyer absorbs risk) | C9: Severe (> 90 % loss in recession)
A10: Control | B10: Lost (buyer integration) | C10: Retained (PE partnership)
A11: Strategic Fit | B11: Synergies realized (~$7–8 M EBITDA savings) | C11: Must grow organically to create value
A12: Market Timing | B12: Favorable → buyers active | C12: Risky → rates high, multiples compressed
A14: Risk Analysis Tab
A15: Risk Type | B15: Strategic Sale Risks | C15: Recap Risks
A16: Integration | B16: Cultural mismatch, key employee turnover | C16: High execution risk from debt burden
A17: Timing | B17: Market multiples could compress before close | C17: Must sustain 8 % growth for 5 yrs
A18: Financial | B18: Buyer pays cash — low risk to founders | C18: Interest rate rise → higher cost of debt
A19: Market | B19: Slight delay risk (~6 mo to close) | C19: Multiple compression (9× → 6×) crushes returns
A20: Downside | B20: None (founders fully cashed out) | C20: PE loses > 90 % in recession
A22: Recommendation Summary
A23: Item | B23: Detail
A24: Likely Buyer | B24: Salesforce / ServiceNow / Adobe
A25: Deal Structure | B25: All-cash acquisition
A26: Deal Price (Target) | B26: ~$2.4 B
A27: Founder Proceeds | B27: ~$1.44 B (60 % ownership)
A28: Timeline | B28: 4–6 months
A29: Risk | B29: Low – no leverage, high market liquidity
A30: Rationale | B30: Certainty of value, immediate liquidity, no execution risk, synergies realized ($7–8 M EBITDA savings).
